{
  "homePageData": [
    {
      "id": "1",
      "title": "Titlexzczc",
      "content": "contentasdasd\nline1aaa\nline2\nline3\n\nline5"
    }
  ],
  "about": [
    {
      "id": "1",
      "content": "test"
    }
  ],
  "contact": [
    {
      "id": "0f62",
      "contactName": "",
      "contactValue": ""
    },
    {
      "id": "c8ab",
      "contactName": "",
      "contactValue": ""
    },
    {
      "id": "6527",
      "contactName": "",
      "contactValue": ""
    },
    {
      "id": "3641",
      "contactName": "",
      "contactValue": ""
    },
    {
      "id": "cc6d",
      "contactName": "123",
      "contactValue": "23"
    },
    {
      "id": "79a7",
      "contactName": "3",
      "contactValue": "4"
    },
    {
      "id": "11a4",
      "contactName": "5",
      "contactValue": "4"
    },
    {
      "id": "b7c2",
      "contactName": "123",
      "contactValue": "1234"
    },
    {
      "id": "81bf",
      "contactName": "t",
      "contactValue": "b"
    }
  ]
}